neathgeohash/Ellipse.py
neathgeohash/Line.py
neathgeohash/__init__.py
neathgeohash/geohash.py
neathgeohash-0.6.4.dist-info/LICENSE
neathgeohash-0.6.4.dist-info/METADATA
neathgeohash-0.6.4.dist-info/WHEEL
neathgeohash-0.6.4.dist-info/top_level.txt
neathgeohash-0.6.4.dist-info/RECORD
