Metadata-Version: 2.1
Name: neathgeohash
Version: 0.6.4
Summary: Python module for interacting with geohashes
Home-page: https://github.com/mpdwulit/neathgeohash
Author: Marek Dwulit
Author-email: marek.dwulit@gmail.com
License: MIT
Download-URL: https://github.com/mpdwulit/neathgeohash/tarball/0.6.4
Keywords: geohash gis eep95 conf95
Platform: UNKNOWN
Classifier: Development Status :: 3 - Alpha
Classifier: Intended Audience :: Developers
Classifier: Programming Language :: Python :: 3
Classifier: License :: OSI Approved :: MIT License
Classifier: Operating System :: OS Independent
Requires-Python: >=3.6
Requires-Dist: geopy
Requires-Dist: numpy
